<manifest alg="2" build="2015.2.1.352" opt="true" iceEnabled="true" iceMarkupVersion="2" iceEnabledOptions="link,responsive" exportTarget="other" domain="grandtour2019.com" resolutions="1x,2x" timestamp="1548693241626">
  <folder name="css">
    <file name="site_global.css" crc="31939975"/>
    <file name="master_a-master.css" crc="229690403" ref="index:2018-wine-list:wineries"/>
    <file name="nomq_preview_master_a-master.css" crc="199937713" ref="index:2018-wine-list:wineries"/>
    <file name="index.css" crc="154839357" ref="index"/>
    <file name="nomq_index.css" crc="448697506" ref="index"/>
    <file name="2018-wine-list.css" crc="4197166095" ref="2018-wine-list"/>
    <file name="nomq_2018-wine-list.css" crc="3822687714" ref="2018-wine-list"/>
    <file name="wineries.css" crc="316845496" ref="wineries"/>
    <file name="nomq_wineries.css" crc="341735783" ref="wineries"/>
  </folder>
  <folder name="fonts">
    <file name="worksans-semibold.woff" crc="305149025"/>
    <file name="worksans-semibold.eot" crc="120615377"/>
    <file name="worksans-regular.woff" crc="283533100"/>
    <file name="worksans-regular.eot" crc="480645326"/>
  </folder>
  <folder name="scripts">
    <file name="jquery-1.8.3.min.js" crc="169078940" ref="index:wineries:2018-wine-list"/>
    <file name="museutils.js" crc="3851988764" ref="index:wineries:2018-wine-list"/>
    <file name="whatinput.js" crc="86476730" ref="index:wineries:2018-wine-list"/>
    <file name="museconfig.js" crc="169177150" ref="index:wineries:2018-wine-list"/>
    <file name="pie.js" crc="3831537696" ref="index:wineries:2018-wine-list"/>
    <file name="jquery.watch.js" crc="3842844514" ref="index:wineries:2018-wine-list"/>
    <file name="webpro.js" crc="4067903014" ref="index:wineries:2018-wine-list"/>
    <file name="musewpdisclosure.js" crc="338211507" ref="index:wineries:2018-wine-list"/>
    <file name="jquery.museresponsive.js" crc="516761069" ref="index:wineries:2018-wine-list"/>
    <file name="require.js" crc="4108833657" ref="index:wineries:2018-wine-list"/>
  </folder>
  <folder name="images">
    <file name="a-master-favicon.ico" crc="4220636928" ref="index"/>
    <file name="grand-tour-logo.png" crc="488851509" seo="true" ref="index:wineries:2018-wine-list"/>
    <file name="grand-tour-logo_2x.png" crc="426736109" seo="true" ref="index:wineries:2018-wine-list"/>
    <file name="gals.jpg" crc="525314005" seo="true" ref="index"/>
    <file name="gals_2x.jpg" crc="94587614" seo="true" ref="index"/>
    <file name="two-men.jpg" crc="4280288586" seo="true" ref="index"/>
    <file name="two-men_2x.jpg" crc="76949990" seo="true" ref="index"/>
    <file name="general-admission.jpg" crc="114310591" seo="true" ref="index"/>
    <file name="general-admission_2x.jpg" crc="4051573715" seo="true" ref="index"/>
    <file name="pour.jpg" crc="3982057700" seo="true" ref="index"/>
    <file name="pour_2x.jpg" crc="513148668" seo="true" ref="index"/>
    <file name="couple.jpg" crc="238825187" seo="true" ref="index"/>
    <file name="couple_2x.jpg" crc="185951753" seo="true" ref="index"/>
    <file name="guy-2-gals.jpg" crc="230019643" seo="true" ref="index"/>
    <file name="guy-2-gals_2x.jpg" crc="3979069591" seo="true" ref="index"/>
    <file name="las-vegas396x248.jpg" crc="3852054889" seo="true" ref="index"/>
    <file name="las-vegas396x248_2x.jpg" crc="3776234913" seo="true" ref="index"/>
    <file name="chicago402x248.jpg" crc="12284335" seo="true" ref="index"/>
    <file name="chicago402x248_2x.jpg" crc="390356503" seo="true" ref="index"/>
    <file name="miami394x248.jpg" crc="59986253" seo="true" ref="index"/>
    <file name="miami394x248_2x.jpg" crc="177597881" seo="true" ref="index"/>
    <file name="reserve-a-room.jpg" crc="103076221" seo="true" ref="index"/>
    <file name="reserve-a-room_2x.jpg" crc="533928308" seo="true" ref="index"/>
    <file name="group-guys.jpg" crc="3994945674" seo="true" ref="index"/>
    <file name="group-guys_2x.jpg" crc="358888680" seo="true" ref="index"/>
    <file name="glass.jpg" crc="348399657" seo="true" ref="index"/>
    <file name="glass_2x.jpg" crc="4106340682" seo="true" ref="index"/>
    <file name="couple-bottles.jpg" crc="4273913946" seo="true" ref="index"/>
    <file name="couple-bottles_2x.jpg" crc="23733355" seo="true" ref="index"/>
    <file name="two-women.jpg" crc="31175698" seo="true" ref="index"/>
    <file name="two-women_2x.jpg" crc="3915405940" seo="true" ref="index"/>
    <file name="grand-tour-logo390x436.png" crc="3824892151" seo="true" ref="index"/>
    <file name="grand-tour-logo390x436_2x.png" crc="426736109" seo="true" ref="index"/>
    <file name="gals307x228.jpg" crc="125201479" seo="true" ref="index"/>
    <file name="gals307x228_2x.jpg" crc="4004285466" seo="true" ref="index"/>
    <file name="two-men308x228.jpg" crc="222479945" seo="true" ref="index"/>
    <file name="two-men308x228_2x.jpg" crc="3837071982" seo="true" ref="index"/>
    <file name="general-admission268x71.jpg" crc="179849685" seo="true" ref="index"/>
    <file name="general-admission268x71_2x.jpg" crc="174858036" seo="true" ref="index"/>
    <file name="pour307x228.jpg" crc="476116325" seo="true" ref="index"/>
    <file name="pour307x228_2x.jpg" crc="115128574" seo="true" ref="index"/>
    <file name="couple402x228.jpg" crc="4129715356" seo="true" ref="index"/>
    <file name="couple402x228_2x.jpg" crc="353842329" seo="true" ref="index"/>
    <file name="guy-2-gals307x228.jpg" crc="4187718542" seo="true" ref="index"/>
    <file name="guy-2-gals307x228_2x.jpg" crc="4085465655" seo="true" ref="index"/>
    <file name="las-vegas338x212.jpg" crc="29970629" seo="true" ref="index"/>
    <file name="las-vegas338x212_2x.jpg" crc="323083990" seo="true" ref="index"/>
    <file name="chicago343x212.jpg" crc="4149097973" seo="true" ref="index"/>
    <file name="chicago343x212_2x.jpg" crc="28771899" seo="true" ref="index"/>
    <file name="miami336x212.jpg" crc="4026135217" seo="true" ref="index"/>
    <file name="miami336x212_2x.jpg" crc="3758507722" seo="true" ref="index"/>
    <file name="reserve-a-room173x43.jpg" crc="3823688185" seo="true" ref="index"/>
    <file name="reserve-a-room173x43_2x.jpg" crc="4095252430" seo="true" ref="index"/>
    <file name="group-guys556x372.jpg" crc="4232612243" seo="true" ref="index"/>
    <file name="group-guys556x372_2x.jpg" crc="440615098" seo="true" ref="index"/>
    <file name="two-women244x346.jpg" crc="316753223" seo="true" ref="index"/>
    <file name="two-women244x346_2x.jpg" crc="4211288841" seo="true" ref="index"/>
    <file name="couple-bottles307x346.jpg" crc="65307335" seo="true" ref="index"/>
    <file name="couple-bottles307x346_2x.jpg" crc="383374738" seo="true" ref="index"/>
    <file name="glass464x721.jpg" crc="308672810" seo="true" ref="index"/>
    <file name="glass464x721_2x.jpg" crc="154676835" seo="true" ref="index"/>
    <file name="grand-tour-logo365x409.png" crc="435221129" seo="true" ref="index"/>
    <file name="grand-tour-logo365x409_2x.png" crc="426736109" seo="true" ref="index"/>
    <file name="gals288x214.jpg" crc="3814535978" seo="true" ref="index"/>
    <file name="gals288x214_2x.jpg" crc="26670548" seo="true" ref="index"/>
    <file name="two-men289x214.jpg" crc="141181918" seo="true" ref="index"/>
    <file name="two-men289x214_2x.jpg" crc="3997885963" seo="true" ref="index"/>
    <file name="general-admission252x66.jpg" crc="3866737605" seo="true" ref="index"/>
    <file name="general-admission252x66_2x.jpg" crc="132451938" seo="true" ref="index"/>
    <file name="pour288x214.jpg" crc="272094435" seo="true" ref="index"/>
    <file name="pour288x214_2x.jpg" crc="416599154" seo="true" ref="index"/>
    <file name="couple377x214.jpg" crc="93029285" seo="true" ref="index"/>
    <file name="couple377x214_2x.jpg" crc="3903726319" seo="true" ref="index"/>
    <file name="guy-2-gals288x214.jpg" crc="157115178" seo="true" ref="index"/>
    <file name="guy-2-gals288x214_2x.jpg" crc="82706368" seo="true" ref="index"/>
    <file name="las-vegas317x199.jpg" crc="3979981374" seo="true" ref="index"/>
    <file name="las-vegas317x199_2x.jpg" crc="274065819" seo="true" ref="index"/>
    <file name="chicago321x199.jpg" crc="3851234855" seo="true" ref="index"/>
    <file name="chicago321x199_2x.jpg" crc="301965489" seo="true" ref="index"/>
    <file name="miami315x199.jpg" crc="266413966" seo="true" ref="index"/>
    <file name="miami315x199_2x.jpg" crc="45169689" seo="true" ref="index"/>
    <file name="reserve-a-room163x40.jpg" crc="300994251" seo="true" ref="index"/>
    <file name="reserve-a-room163x40_2x.jpg" crc="4133615233" seo="true" ref="index"/>
    <file name="group-guys521x348.jpg" crc="451229340" seo="true" ref="index"/>
    <file name="group-guys521x348_2x.jpg" crc="3998498492" seo="true" ref="index"/>
    <file name="two-women229x324.jpg" crc="3242480" seo="true" ref="index"/>
    <file name="two-women229x324_2x.jpg" crc="3998432719" seo="true" ref="index"/>
    <file name="couple-bottles288x324.jpg" crc="216773731" seo="true" ref="index"/>
    <file name="couple-bottles288x324_2x.jpg" crc="66433178" seo="true" ref="index"/>
    <file name="glass435x676.jpg" crc="3835964519" seo="true" ref="index"/>
    <file name="glass435x676_2x.jpg" crc="3916147180" seo="true" ref="index"/>
    <file name="grand-tour-logo323x362.png" crc="4204466342" seo="true" ref="index"/>
    <file name="grand-tour-logo323x362_2x.png" crc="426736109" seo="true" ref="index"/>
    <file name="gals255x190.jpg" crc="243218630" seo="true" ref="index"/>
    <file name="gals255x190_2x.jpg" crc="3964578664" seo="true" ref="index"/>
    <file name="two-men256x190.jpg" crc="3838341223" seo="true" ref="index"/>
    <file name="two-men256x190_2x.jpg" crc="4150737944" seo="true" ref="index"/>
    <file name="general-admission223x59.jpg" crc="330826912" seo="true" ref="index"/>
    <file name="general-admission223x59_2x.jpg" crc="4204443045" seo="true" ref="index"/>
    <file name="pour255x190.jpg" crc="4097147798" seo="true" ref="index"/>
    <file name="pour255x190_2x.jpg" crc="4015362649" seo="true" ref="index"/>
    <file name="couple334x190.jpg" crc="4173249521" seo="true" ref="index"/>
    <file name="couple334x190_2x.jpg" crc="122691866" seo="true" ref="index"/>
    <file name="guy-2-gals255x190.jpg" crc="3960510180" seo="true" ref="index"/>
    <file name="guy-2-gals255x190_2x.jpg" crc="4071222620" seo="true" ref="index"/>
    <file name="las-vegas280x176.jpg" crc="3889849377" seo="true" ref="index"/>
    <file name="las-vegas280x176_2x.jpg" crc="255690361" seo="true" ref="index"/>
    <file name="chicago285x176.jpg" crc="3964891885" seo="true" ref="index"/>
    <file name="chicago285x176_2x.jpg" crc="4239314151" seo="true" ref="index"/>
    <file name="miami279x176.jpg" crc="324132580" seo="true" ref="index"/>
    <file name="miami279x176_2x.jpg" crc="3860611537" seo="true" ref="index"/>
    <file name="reserve-a-room144x36.jpg" crc="469161576" seo="true" ref="index"/>
    <file name="reserve-a-room144x36_2x.jpg" crc="293642288" seo="true" ref="index"/>
    <file name="group-guys461x309.jpg" crc="3992318027" seo="true" ref="index"/>
    <file name="group-guys461x309_2x.jpg" crc="387141831" seo="true" ref="index"/>
    <file name="two-women203x287.jpg" crc="4174160578" seo="true" ref="index"/>
    <file name="two-women203x287_2x.jpg" crc="536532785" seo="true" ref="index"/>
    <file name="couple-bottles255x287.jpg" crc="137960081" seo="true" ref="index"/>
    <file name="couple-bottles255x287_2x.jpg" crc="393571712" seo="true" ref="index"/>
    <file name="glass385x598.jpg" crc="51503839" seo="true" ref="index"/>
    <file name="glass385x598_2x.jpg" crc="261141969" seo="true" ref="index"/>
    <file name="grand-tour-logo292x327.png" crc="3959003690" seo="true" ref="index"/>
    <file name="grand-tour-logo292x327_2x.png" crc="3974700562" seo="true" ref="index"/>
    <file name="gals231x171.jpg" crc="4118459475" seo="true" ref="index"/>
    <file name="gals231x171_2x.jpg" crc="279884384" seo="true" ref="index"/>
    <file name="two-men231x171.jpg" crc="458819669" seo="true" ref="index"/>
    <file name="two-men231x171_2x.jpg" crc="3965886491" seo="true" ref="index"/>
    <file name="general-admission201x53.jpg" crc="4262656579" seo="true" ref="index"/>
    <file name="general-admission201x53_2x.jpg" crc="331151051" seo="true" ref="index"/>
    <file name="pour231x171.jpg" crc="84601949" seo="true" ref="index"/>
    <file name="pour231x171_2x.jpg" crc="210935741" seo="true" ref="index"/>
    <file name="couple301x171.jpg" crc="4152739094" seo="true" ref="index"/>
    <file name="couple301x171_2x.jpg" crc="4066536981" seo="true" ref="index"/>
    <file name="guy-2-gals231x171.jpg" crc="3848637002" seo="true" ref="index"/>
    <file name="guy-2-gals231x171_2x.jpg" crc="3844012708" seo="true" ref="index"/>
    <file name="las-vegas253x159.jpg" crc="354646465" seo="true" ref="index"/>
    <file name="las-vegas253x159_2x.jpg" crc="62433046" seo="true" ref="index"/>
    <file name="chicago257x159.jpg" crc="482291266" seo="true" ref="index"/>
    <file name="chicago257x159_2x.jpg" crc="4272040654" seo="true" ref="index"/>
    <file name="miami252x159.jpg" crc="3762744112" seo="true" ref="index"/>
    <file name="miami252x159_2x.jpg" crc="3828763932" seo="true" ref="index"/>
    <file name="reserve-a-room130x32.jpg" crc="488739467" seo="true" ref="index"/>
    <file name="reserve-a-room130x32_2x.jpg" crc="272362568" seo="true" ref="index"/>
    <file name="group-guys417x279.jpg" crc="483618104" seo="true" ref="index"/>
    <file name="group-guys417x279_2x.jpg" crc="4202943464" seo="true" ref="index"/>
    <file name="two-women183x260.jpg" crc="171589931" seo="true" ref="index"/>
    <file name="two-women183x260_2x.jpg" crc="4078507529" seo="true" ref="index"/>
    <file name="couple-bottles230x259.jpg" crc="391927623" seo="true" ref="index"/>
    <file name="couple-bottles230x259_2x.jpg" crc="4221389627" seo="true" ref="index"/>
    <file name="glass348x541.jpg" crc="3789483391" seo="true" ref="index"/>
    <file name="glass348x541_2x.jpg" crc="330081849" seo="true" ref="index"/>
    <file name="grand-tour-logo254x284.png" crc="4015831793" seo="true" ref="index"/>
    <file name="grand-tour-logo254x284_2x.png" crc="44187145" seo="true" ref="index"/>
    <file name="gals200x149.jpg" crc="3831704163" seo="true" ref="index"/>
    <file name="gals200x149_2x.jpg" crc="16367333" seo="true" ref="index"/>
    <file name="two-men201x149.jpg" crc="242959731" seo="true" ref="index"/>
    <file name="two-men201x149_2x.jpg" crc="3821313461" seo="true" ref="index"/>
    <file name="general-admission175x46.jpg" crc="361983466" seo="true" ref="index"/>
    <file name="general-admission175x46_2x.jpg" crc="3975433434" seo="true" ref="index"/>
    <file name="pour200x149.jpg" crc="3823674112" seo="true" ref="index"/>
    <file name="pour200x149_2x.jpg" crc="4120835944" seo="true" ref="index"/>
    <file name="couple262x149.jpg" crc="3930766155" seo="true" ref="index"/>
    <file name="couple262x149_2x.jpg" crc="317784378" seo="true" ref="index"/>
    <file name="guy-2-gals200x149.jpg" crc="4191109732" seo="true" ref="index"/>
    <file name="guy-2-gals200x149_2x.jpg" crc="4129956854" seo="true" ref="index"/>
    <file name="las-vegas220x138.jpg" crc="4281676463" seo="true" ref="index"/>
    <file name="las-vegas220x138_2x.jpg" crc="3788826611" seo="true" ref="index"/>
    <file name="chicago223x138.jpg" crc="3879763718" seo="true" ref="index"/>
    <file name="chicago223x138_2x.jpg" crc="197055955" seo="true" ref="index"/>
    <file name="miami219x138.jpg" crc="4187448304" seo="true" ref="index"/>
    <file name="miami219x138_2x.jpg" crc="51522378" seo="true" ref="index"/>
    <file name="reserve-a-room113x28.jpg" crc="342744387" seo="true" ref="index"/>
    <file name="reserve-a-room113x28_2x.jpg" crc="132616616" seo="true" ref="index"/>
    <file name="group-guys362x242.jpg" crc="4211834632" seo="true" ref="index"/>
    <file name="group-guys362x242_2x.jpg" crc="516285450" seo="true" ref="index"/>
    <file name="two-women159x226.jpg" crc="4245793067" seo="true" ref="index"/>
    <file name="two-women159x226_2x.jpg" crc="3966284467" seo="true" ref="index"/>
    <file name="couple-bottles200x225.jpg" crc="36061604" seo="true" ref="index"/>
    <file name="couple-bottles200x225_2x.jpg" crc="37050611" seo="true" ref="index"/>
    <file name="glass303x469.jpg" crc="4112683293" seo="true" ref="index"/>
    <file name="glass303x469_2x.jpg" crc="3970465328" seo="true" ref="index"/>
    <file name="grand-tour-logo216x242.png" crc="494052740" seo="true" ref="index"/>
    <file name="grand-tour-logo216x242_2x.png" crc="195693385" seo="true" ref="index"/>
    <file name="gals171x127.jpg" crc="142689868" seo="true" ref="index"/>
    <file name="gals171x127_2x.jpg" crc="417206165" seo="true" ref="index"/>
    <file name="two-men171x127.jpg" crc="3901113485" seo="true" ref="index"/>
    <file name="two-men171x127_2x.jpg" crc="149405268" seo="true" ref="index"/>
    <file name="general-admission149x39.jpg" crc="4257235031" seo="true" ref="index"/>
    <file name="general-admission149x39_2x.jpg" crc="3884797264" seo="true" ref="index"/>
    <file name="pour171x127.jpg" crc="381926663" seo="true" ref="index"/>
    <file name="pour171x127_2x.jpg" crc="76494469" seo="true" ref="index"/>
    <file name="couple223x127.jpg" crc="3797527888" seo="true" ref="index"/>
    <file name="couple223x127_2x.jpg" crc="20969858" seo="true" ref="index"/>
    <file name="guy-2-gals171x127.jpg" crc="524446050" seo="true" ref="index"/>
    <file name="guy-2-gals171x127_2x.jpg" crc="99868947" seo="true" ref="index"/>
    <file name="las-vegas188x118.jpg" crc="475340596" seo="true" ref="index"/>
    <file name="las-vegas188x118_2x.jpg" crc="3971809721" seo="true" ref="index"/>
    <file name="chicago190x118.jpg" crc="3935078823" seo="true" ref="index"/>
    <file name="chicago190x118_2x.jpg" crc="3863097614" seo="true" ref="index"/>
    <file name="miami187x118.jpg" crc="355524844" seo="true" ref="index"/>
    <file name="miami187x118_2x.jpg" crc="230654556" seo="true" ref="index"/>
    <file name="reserve-a-room123x31.jpg" crc="39203554" seo="true" ref="index"/>
    <file name="reserve-a-room123x31_2x.jpg" crc="374175511" seo="true" ref="index"/>
    <file name="group-guys309x206.jpg" crc="4268191016" seo="true" ref="index"/>
    <file name="group-guys309x206_2x.jpg" crc="335081323" seo="true" ref="index"/>
    <file name="two-women136x192.jpg" crc="447820964" seo="true" ref="index"/>
    <file name="two-women136x192_2x.jpg" crc="4071499941" seo="true" ref="index"/>
    <file name="couple-bottles170x192.jpg" crc="4233816170" seo="true" ref="index"/>
    <file name="couple-bottles170x192_2x.jpg" crc="34458115" seo="true" ref="index"/>
    <file name="glass258x400.jpg" crc="4177779681" seo="true" ref="index"/>
    <file name="glass258x400_2x.jpg" crc="34006541" seo="true" ref="index"/>
    <file name="top-pour-mobile.jpg" crc="3838224444" seo="true" ref="index:wineries:2018-wine-list"/>
    <file name="top-pour-mobile_2x.jpg" crc="4006091579" seo="true" ref="index:wineries:2018-wine-list"/>
    <file name="grand-tour-logo314x352.png" crc="3793437145" seo="true" ref="index"/>
    <file name="grand-tour-logo314x352_2x.png" crc="426736109" seo="true" ref="index"/>
    <file name="gals205x152.jpg" crc="72077642" seo="true" ref="index"/>
    <file name="gals205x152_2x.jpg" crc="116292356" seo="true" ref="index"/>
    <file name="two-men205x152.jpg" crc="255415345" seo="true" ref="index"/>
    <file name="two-men205x152_2x.jpg" crc="3769013953" seo="true" ref="index"/>
    <file name="general-admission300x79.jpg" crc="492419292" seo="true" ref="index"/>
    <file name="general-admission300x79_2x.jpg" crc="4031112574" seo="true" ref="index"/>
    <file name="couple414x236.jpg" crc="4051655892" seo="true" ref="index"/>
    <file name="couple414x236_2x.jpg" crc="128040447" seo="true" ref="index"/>
    <file name="pour204x152.jpg" crc="85835772" seo="true" ref="index"/>
    <file name="pour204x152_2x.jpg" crc="3836014678" seo="true" ref="index"/>
    <file name="guy-2-gals204x152.jpg" crc="214157881" seo="true" ref="index"/>
    <file name="guy-2-gals204x152_2x.jpg" crc="490685722" seo="true" ref="index"/>
    <file name="las-vegas.jpg" crc="228422615" seo="true" ref="index"/>
    <file name="las-vegas_2x.jpg" crc="4221990843" seo="true" ref="index"/>
    <file name="reserve-a-room194x48.jpg" crc="133751345" seo="true" ref="index"/>
    <file name="reserve-a-room194x48_2x.jpg" crc="4044805315" seo="true" ref="index"/>
    <file name="chicago.jpg" crc="4015066687" seo="true" ref="index"/>
    <file name="chicago_2x.jpg" crc="504936944" seo="true" ref="index"/>
    <file name="miami.jpg" crc="3885847239" seo="true" ref="index"/>
    <file name="miami_2x.jpg" crc="3930897363" seo="true" ref="index"/>
    <file name="group-guys414x277.jpg" crc="155030342" seo="true" ref="index"/>
    <file name="group-guys414x277_2x.jpg" crc="4089331115" seo="true" ref="index"/>
    <file name="glass414x643.jpg" crc="116162887" seo="true" ref="index"/>
    <file name="glass414x643_2x.jpg" crc="3778003660" seo="true" ref="index"/>
    <file name="two-women181x256.jpg" crc="4132044712" seo="true" ref="index"/>
    <file name="two-women181x256_2x.jpg" crc="3902749153" seo="true" ref="index"/>
    <file name="couple-bottles227x256.jpg" crc="3845395453" seo="true" ref="index"/>
    <file name="couple-bottles227x256_2x.jpg" crc="3968318528" seo="true" ref="index"/>
    <file name="top-pour-mobile-crop-u37869.jpg" crc="343848003" ref="index:wineries:2018-wine-list"/>
    <file name="top-pour-mobile-crop-u37869_2x.jpg" crc="3786512306" ref="index:wineries:2018-wine-list"/>
    <file name="grand-tour-logo307x344.png" crc="3847668362" seo="true" ref="index"/>
    <file name="grand-tour-logo307x344_2x.png" crc="204725216" seo="true" ref="index"/>
    <file name="gals186x138.jpg" crc="137550307" seo="true" ref="index"/>
    <file name="gals186x138_2x.jpg" crc="4185525238" seo="true" ref="index"/>
    <file name="two-men186x138.jpg" crc="3782346931" seo="true" ref="index"/>
    <file name="two-men186x138_2x.jpg" crc="235461448" seo="true" ref="index"/>
    <file name="couple375x213.jpg" crc="115928394" seo="true" ref="index"/>
    <file name="couple375x213_2x.jpg" crc="46314084" seo="true" ref="index"/>
    <file name="pour185x137.jpg" crc="203167584" seo="true" ref="index"/>
    <file name="pour185x137_2x.jpg" crc="141864226" seo="true" ref="index"/>
    <file name="guy-2-gals185x137.jpg" crc="361300086" seo="true" ref="index"/>
    <file name="guy-2-gals185x137_2x.jpg" crc="182707860" seo="true" ref="index"/>
    <file name="las-vegas375x236.jpg" crc="56254656" seo="true" ref="index"/>
    <file name="las-vegas375x236_2x.jpg" crc="3885309072" seo="true" ref="index"/>
    <file name="chicago375x232.jpg" crc="3851047439" seo="true" ref="index"/>
    <file name="chicago375x232_2x.jpg" crc="312771716" seo="true" ref="index"/>
    <file name="miami375x236.jpg" crc="4243829920" seo="true" ref="index"/>
    <file name="miami375x236_2x.jpg" crc="23484714" seo="true" ref="index"/>
    <file name="group-guys375x251.jpg" crc="34181697" seo="true" ref="index"/>
    <file name="group-guys375x251_2x.jpg" crc="95088570" seo="true" ref="index"/>
    <file name="glass375x583.jpg" crc="4098044913" seo="true" ref="index"/>
    <file name="glass375x583_2x.jpg" crc="4171358834" seo="true" ref="index"/>
    <file name="two-women164x233.jpg" crc="350215139" seo="true" ref="index"/>
    <file name="two-women164x233_2x.jpg" crc="3814051688" seo="true" ref="index"/>
    <file name="couple-bottles206x232.jpg" crc="51966544" seo="true" ref="index"/>
    <file name="couple-bottles206x232_2x.jpg" crc="4286115516" seo="true" ref="index"/>
    <file name="grand-tour-logo253x284.png" crc="3951854788" seo="true" ref="index"/>
    <file name="grand-tour-logo253x284_2x.png" crc="4278859817" seo="true" ref="index"/>
    <file name="gals158x118.jpg" crc="286719499" seo="true" ref="index"/>
    <file name="gals158x118_2x.jpg" crc="452521268" seo="true" ref="index"/>
    <file name="two-men159x118.jpg" crc="4119785415" seo="true" ref="index"/>
    <file name="two-men159x118_2x.jpg" crc="209132264" seo="true" ref="index"/>
    <file name="general-admission240x63.jpg" crc="4131594809" seo="true" ref="index"/>
    <file name="general-admission240x63_2x.jpg" crc="299319607" seo="true" ref="index"/>
    <file name="couple320x182.jpg" crc="3967122521" seo="true" ref="index"/>
    <file name="couple320x182_2x.jpg" crc="3975078141" seo="true" ref="index"/>
    <file name="pour157x117.jpg" crc="150808482" seo="true" ref="index"/>
    <file name="pour157x117_2x.jpg" crc="3832624658" seo="true" ref="index"/>
    <file name="guy-2-gals157x117.jpg" crc="410860946" seo="true" ref="index"/>
    <file name="guy-2-gals157x117_2x.jpg" crc="319254155" seo="true" ref="index"/>
    <file name="las-vegas320x201.jpg" crc="40384016" seo="true" ref="index"/>
    <file name="las-vegas320x201_2x.jpg" crc="169238204" seo="true" ref="index"/>
    <file name="reserve-a-room158x39.jpg" crc="357734692" seo="true" ref="index"/>
    <file name="reserve-a-room158x39_2x.jpg" crc="4198464998" seo="true" ref="index"/>
    <file name="chicago320x198.jpg" crc="126074775" seo="true" ref="index"/>
    <file name="chicago320x198_2x.jpg" crc="4155152852" seo="true" ref="index"/>
    <file name="miami320x202.jpg" crc="3932519027" seo="true" ref="index"/>
    <file name="miami320x202_2x.jpg" crc="504471052" seo="true" ref="index"/>
    <file name="reserve-a-room155x39.jpg" crc="370897476" seo="true" ref="index"/>
    <file name="reserve-a-room155x39_2x.jpg" crc="4032664603" seo="true" ref="index"/>
    <file name="group-guys320x214.jpg" crc="4028443741" seo="true" ref="index"/>
    <file name="group-guys320x214_2x.jpg" crc="462677058" seo="true" ref="index"/>
    <file name="glass320x497.jpg" crc="4155528737" seo="true" ref="index"/>
    <file name="glass320x497_2x.jpg" crc="4030904351" seo="true" ref="index"/>
    <file name="two-women140x198.jpg" crc="4022009038" seo="true" ref="index"/>
    <file name="two-women140x198_2x.jpg" crc="192743651" seo="true" ref="index"/>
    <file name="couple-bottles175x198.jpg" crc="501241757" seo="true" ref="index"/>
    <file name="couple-bottles175x198_2x.jpg" crc="263178278" seo="true" ref="index"/>
    <file name="blank.gif" crc="4208392903" ref="index:wineries:2018-wine-list"/>
    <file name="top-pour2.jpg" crc="227841194" seo="true" ref="index:wineries:2018-wine-list"/>
    <file name="top-pour2_2x.jpg" crc="207408018" seo="true" ref="index:wineries:2018-wine-list"/>
    <file name="pour-photo-w-overlay2-crop-u38785.jpg" crc="275951787" ref="index"/>
    <file name="top-pour21024x683.jpg" crc="41519988" seo="true" ref="index"/>
    <file name="top-pour21024x683_2x.jpg" crc="3963260280" seo="true" ref="index"/>
    <file name="pour-photo-w-overlay21024x577.jpg" crc="4072556706" seo="true" ref="index"/>
    <file name="top-pour2960x641.jpg" crc="340754301" seo="true" ref="index"/>
    <file name="top-pour2960x641_2x.jpg" crc="3959745041" seo="true" ref="index"/>
    <file name="pour-photo-w-overlay2960x541.jpg" crc="13175219" seo="true" ref="index"/>
    <file name="top-pour2851x567.jpg" crc="4247112567" seo="true" ref="index"/>
    <file name="top-pour2851x567_2x.jpg" crc="4257021291" seo="true" ref="index"/>
    <file name="pour-photo-w-overlay2850x479.jpg" crc="24060413" seo="true" ref="index"/>
    <file name="top-pour2768x513.jpg" crc="3974030132" seo="true" ref="index"/>
    <file name="top-pour2768x513_2x.jpg" crc="43900605" seo="true" ref="index"/>
    <file name="pour-photo-w-overlay2768x433.jpg" crc="4028454757" seo="true" ref="index"/>
    <file name="top-pour2667x445.jpg" crc="4116287492" seo="true" ref="index"/>
    <file name="top-pour2667x445_2x.jpg" crc="249681726" seo="true" ref="index"/>
    <file name="pour-photo-w-overlay2667x376.jpg" crc="3812081646" seo="true" ref="index"/>
    <file name="top-pour2568x379.jpg" crc="150053068" seo="true" ref="index"/>
    <file name="top-pour2568x379_2x.jpg" crc="4135373421" seo="true" ref="index"/>
    <file name="pour-photo-w-overlay2568x320.jpg" crc="7954833" seo="true" ref="index"/>
    <file name="sign-up2.png" crc="33439631" seo="true" ref="index:wineries:2018-wine-list"/>
    <file name="sign-up2_2x.png" crc="4171332995" seo="true" ref="index:wineries:2018-wine-list"/>
    <file name="sign-up2163x162.png" crc="280584350" seo="true" ref="index"/>
    <file name="sign-up2163x162_2x.png" crc="99925524" seo="true" ref="index"/>
    <file name="sign-up2152x152.png" crc="128787596" seo="true" ref="index"/>
    <file name="sign-up2152x152_2x.png" crc="506468707" seo="true" ref="index"/>
    <file name="sign-up2135x135.png" crc="4147631951" seo="true" ref="index"/>
    <file name="sign-up2135x135_2x.png" crc="431822130" seo="true" ref="index"/>
    <file name="sign-up2122x122.png" crc="399245749" seo="true" ref="index"/>
    <file name="sign-up2122x122_2x.png" crc="3912188056" seo="true" ref="index"/>
    <file name="sign-up2106x106.png" crc="3791929568" seo="true" ref="index"/>
    <file name="sign-up2106x106_2x.png" crc="3905287142" seo="true" ref="index"/>
    <file name="sign-up290x90.png" crc="4000204936" seo="true" ref="index"/>
    <file name="sign-up290x90_2x.png" crc="300006292" seo="true" ref="index"/>
    <file name="sign-up2109x109.png" crc="356293176" seo="true" ref="index"/>
    <file name="sign-up2109x109_2x.png" crc="175963810" seo="true" ref="index"/>
    <file name="wine-photo-mobile414x342.jpg" crc="3902326631" seo="true" ref="index"/>
    <file name="wine-photo-mobile_2x.jpg" crc="328130914" seo="true" ref="index"/>
    <file name="240414x135.png" crc="4110441805" seo="true" ref="index"/>
    <file name="240_2x.png" crc="4110441805" seo="true" ref="index"/>
    <file name="sign-up295x94.png" crc="3821065682" seo="true" ref="index"/>
    <file name="sign-up295x94_2x.png" crc="4044303857" seo="true" ref="index"/>
    <file name="wine-photo-mobile375x310.jpg" crc="4113065100" seo="true" ref="index"/>
    <file name="wine-photo-mobile375x310_2x.jpg" crc="4115677399" seo="true" ref="index"/>
    <file name="240375x122.png" crc="4110441805" seo="true" ref="index"/>
    <file name="240375x122_2x.png" crc="4110441805" seo="true" ref="index"/>
    <file name="sign-up283x83.png" crc="194276575" seo="true" ref="index"/>
    <file name="sign-up283x83_2x.png" crc="3909787371" seo="true" ref="index"/>
    <file name="wine-photo-mobile320x264.jpg" crc="377049134" seo="true" ref="index"/>
    <file name="wine-photo-mobile320x264_2x.jpg" crc="3996400499" seo="true" ref="index"/>
    <file name="240320x104.png" crc="3869415984" seo="true" ref="index"/>
    <file name="240320x104_2x.png" crc="4110441805" seo="true" ref="index"/>
    <file name="vip325-2.jpg" crc="458727619" seo="true" ref="index"/>
    <file name="vip325-2_2x.jpg" crc="280602113" seo="true" ref="index"/>
    <file name="vip325-2268x71.jpg" crc="390418841" seo="true" ref="index"/>
    <file name="vip325-2268x71_2x.jpg" crc="63421570" seo="true" ref="index"/>
    <file name="vip325-2252x66.jpg" crc="3947879475" seo="true" ref="index"/>
    <file name="vip325-2252x66_2x.jpg" crc="3969526176" seo="true" ref="index"/>
    <file name="vip325-2223x59.jpg" crc="4169405489" seo="true" ref="index"/>
    <file name="vip325-2223x59_2x.jpg" crc="3928955805" seo="true" ref="index"/>
    <file name="vip325-2201x53.jpg" crc="3966888345" seo="true" ref="index"/>
    <file name="vip325-2201x53_2x.jpg" crc="489550976" seo="true" ref="index"/>
    <file name="vip325-2175x46.jpg" crc="3809690606" seo="true" ref="index"/>
    <file name="vip325-2175x46_2x.jpg" crc="349521009" seo="true" ref="index"/>
    <file name="vip325-2149x39.jpg" crc="3795835971" seo="true" ref="index"/>
    <file name="vip325-2149x39_2x.jpg" crc="495149915" seo="true" ref="index"/>
    <file name="vip325-2300x79.jpg" crc="103911127" seo="true" ref="index"/>
    <file name="vip325-2300x79_2x.jpg" crc="4134898082" seo="true" ref="index"/>
    <file name="vip325-2301x79.jpg" crc="103911127" seo="true" ref="index"/>
    <file name="vip325-2301x79_2x.jpg" crc="168988548" seo="true" ref="index"/>
    <file name="vip325-2240x63.jpg" crc="71018855" seo="true" ref="index"/>
    <file name="vip325-2240x63_2x.jpg" crc="305734897" seo="true" ref="index"/>
    <file name="wineries253x74.png" crc="395883286" seo="true" ref="index"/>
    <file name="wineries253x74_2x.png" crc="4035474522" seo="true" ref="index"/>
    <file name="wineries237x69.png" crc="116817008" seo="true" ref="index"/>
    <file name="wineries237x69_2x.png" crc="4035474522" seo="true" ref="index"/>
    <file name="wineries210x61.png" crc="3851273022" seo="true" ref="index"/>
    <file name="wineries210x61_2x.png" crc="4035474522" seo="true" ref="index"/>
    <file name="wineries190x56.png" crc="340563284" seo="true" ref="index"/>
    <file name="wineries190x56_2x.png" crc="4035474522" seo="true" ref="index"/>
    <file name="wineries165x48.png" crc="40725373" seo="true" ref="index"/>
    <file name="wineries165x48_2x.png" crc="4035474522" seo="true" ref="index"/>
    <file name="wineries141x41.png" crc="305015637" seo="true" ref="index"/>
    <file name="wineries141x41_2x.png" crc="3858545151" seo="true" ref="index"/>
    <file name="wineries.png" crc="4114666904" seo="true" ref="index"/>
    <file name="wineries_2x.png" crc="4035474522" seo="true" ref="index"/>
    <file name="wineries213x62.png" crc="3871101687" seo="true" ref="index"/>
    <file name="wineries213x62_2x.png" crc="4035474522" seo="true" ref="index"/>
    <file name="wineries203x59.png" crc="240587315" seo="true" ref="index"/>
    <file name="wineries203x59_2x.png" crc="4035474522" seo="true" ref="index"/>
    <file name="wineries176x52.png" crc="534100359" seo="true" ref="index"/>
    <file name="wineries176x52_2x.png" crc="4035474522" seo="true" ref="index"/>
  </folder>
  <file name="index.html" crc="3931125055" seo="true" mt="1548693182723" redirect="true"/>
  <file name="wineries.html" crc="4042101270" seo="true" mt="1548692698042" redirect="true"/>
  <file name="2018-wine-list.html" crc="349520469" seo="true" mt="1548692698042" redirect="true"/>
</manifest>